kolja_aws/__init__.py
kolja_aws/__version__.py
kolja_aws/backup_manager.py
kolja_aws/diagnose.py
kolja_aws/interactive_config.py
kolja_aws/kolja_login.py
kolja_aws/post_install.py
kolja_aws/profile_loader.py
kolja_aws/profile_switcher.py
kolja_aws/script_generator.py
kolja_aws/session_config.py
kolja_aws/shell_detector.py
kolja_aws/shell_exceptions.py
kolja_aws/shell_installer.py
kolja_aws/shell_integration.py
kolja_aws/shell_models.py
kolja_aws/sso_exceptions.py
kolja_aws/terminal_ui.py
kolja_aws/user_experience.py
kolja_aws/utils.py
kolja_aws/validators.py
kolja_aws-0.4.3.dist-info/METADATA
kolja_aws-0.4.3.dist-info/WHEEL
kolja_aws-0.4.3.dist-info/entry_points.txt
kolja_aws-0.4.3.dist-info/RECORD
